README.txt
setup.cfg
setup.py
docs/HISTORY.txt
docs/INSTALL.txt
docs/LICENSE.GPL
docs/LICENSE.txt
niteoweb/__init__.py
niteoweb.downloadcounter.egg-info/PKG-INFO
niteoweb.downloadcounter.egg-info/SOURCES.txt
niteoweb.downloadcounter.egg-info/dependency_links.txt
niteoweb.downloadcounter.egg-info/entry_points.txt
niteoweb.downloadcounter.egg-info/namespace_packages.txt
niteoweb.downloadcounter.egg-info/not-zip-safe
niteoweb.downloadcounter.egg-info/requires.txt
niteoweb.downloadcounter.egg-info/top_level.txt
niteoweb/downloadcounter/__init__.py
niteoweb/downloadcounter/configure.zcml
niteoweb/downloadcounter/extender.py
niteoweb/downloadcounter/tests.py
niteoweb/downloadcounter/browser/__init__.py
niteoweb/downloadcounter/browser/configure.zcml
niteoweb/downloadcounter/browser/download_count.pt
niteoweb/downloadcounter/browser/interfaces.py
niteoweb/downloadcounter/browser/viewlets.py
niteoweb/downloadcounter/profiles/default/skins.xml
niteoweb/downloadcounter/profiles/default/viewlets.xml
niteoweb/downloadcounter/skins/downloadcounter/at_download.py