Metadata-Version: 1.0
Name: niteoweb.downloadcounter
Version: 1.0
Summary: Counts how many time was a File content type downloaded and displays this number on File view page.
Home-page: http://plone.org/products/niteoweb.downloadcounter
Author: NiteoWeb Ltd.
Author-email: info@niteoweb.com
License: GPL
Keywords: Plone
Platform: UNKNOWN
Classifier: Framework :: Plone
Classifier: Programming Language :: Python
